lprocess/EDA.py
lprocess/__init__.py
lprocess/hello.py
lprocess/lprocess.py
lprocess-0.0.11.dist-info/METADATA
lprocess-0.0.11.dist-info/WHEEL
lprocess-0.0.11.dist-info/top_level.txt
lprocess-0.0.11.dist-info/RECORD
