Metadata-Version: 2.1
Name: lprocess
Version: 0.0.11
Summary: Data Preprocessing library that makes EDA easy for all
Home-page: UNKNOWN
Author: Chirag Patil
Author-email: chiragnpatil@gmail.com
License: UNKNOWN
Keywords: python
Platform: UNKNOWN
Classifier: Development Status :: 1 - Planning
Classifier: Intended Audience :: Developers
Classifier: Programming Language :: Python :: 3
Classifier: Operating System :: Unix
Classifier: Operating System :: MacOS :: MacOS X
Classifier: Operating System :: Microsoft :: Windows
Requires-Dist: matplotlib
Requires-Dist: numpy
Requires-Dist: pandas
Requires-Dist: seaborn
